koji-stubs/__init__.pyi
koji-stubs/_version.pyi
koji-stubs/arch.pyi
koji-stubs/context.pyi
koji-stubs/daemon.pyi
koji-stubs/plugin.pyi
koji-stubs/policy.pyi
koji-stubs/py.typed
koji-stubs/rpmdiff.pyi
koji-stubs/server.pyi
koji-stubs/tasks.pyi
koji-stubs/util.pyi
koji-stubs/xmlrpcplus.pyi
koji_cli-stubs/__init__.pyi
koji_cli-stubs/commands.pyi
koji_cli-stubs/lib.pyi
koji_cli-stubs/py.typed
koji_types/__init__.py
koji_types/arch.py
koji_types/cli.py
koji_types/hub.py
koji_types/plugin.py
koji_types/policy.py
koji_types/protocols.py
koji_types/protocols.pyi
koji_types/py.typed
koji_types/rpm.py
kojihub-stubs/__init__.pyi
kojihub-stubs/auth.pyi
kojihub-stubs/db.pyi
kojihub-stubs/kojihub.pyi
kojihub-stubs/kojixmlrpc.pyi
kojihub-stubs/py.typed
preoccupied.koji_typing-1.35.0.dist-info/LICENSE
preoccupied.koji_typing-1.35.0.dist-info/METADATA
preoccupied.koji_typing-1.35.0.dist-info/WHEEL
preoccupied.koji_typing-1.35.0.dist-info/top_level.txt
preoccupied.koji_typing-1.35.0.dist-info/RECORD
