Metadata-Version: 2.1
Name: preoccupied.koji-typing
Version: 1.35.0
Summary: types and annotations for the koji build system
Home-page: https://github.com/obriencj/koji-typing
Author: Christopher O'Brien
Author-email: obriencj@preoccupied.net
License: GNU General Public License v3 (GPLv3)
Project-URL: Source, https://github.com/obriencj/koji-typing
Project-URL: Issues, https://github.com/obriencj/koji-typing/issues
Platform: any
Classifier: Development Status :: 4 - Beta
Classifier: Environment :: Console
Classifier: Intended Audience :: Developers
Classifier: License :: OSI Approved :: GNU General Public License v3 (GPLv3)
Classifier: Natural Language :: English
Classifier: Programming Language :: Python :: 3
Classifier: Programming Language :: Python :: 3.6
Classifier: Programming Language :: Python :: 3.7
Classifier: Programming Language :: Python :: 3.8
Classifier: Programming Language :: Python :: 3.9
Classifier: Programming Language :: Python :: 3.10
Classifier: Programming Language :: Python :: 3.11
Classifier: Topic :: Software Development :: Build Tools
Classifier: Topic :: Utilities
License-File: LICENSE
Requires-Dist: koji>=1.35.0
Requires-Dist: typing_extensions
Provides-Extra: typedeps
Requires-Dist: types-psycopg2; extra == "typedeps"
Requires-Dist: types-python-dateutil; extra == "typedeps"
Requires-Dist: types-requests; extra == "typedeps"
Requires-Dist: types-six; extra == "typedeps"
